small_probs/__init__.py
small_probs/estimates.py
small_probs/probability.py
small_probs_wlad111-0.2.0.dist-info/LICENSE
small_probs_wlad111-0.2.0.dist-info/METADATA
small_probs_wlad111-0.2.0.dist-info/WHEEL
small_probs_wlad111-0.2.0.dist-info/top_level.txt
small_probs_wlad111-0.2.0.dist-info/RECORD
