Metadata-Version: 2.1
Name: small-probs-wlad111
Version: 0.2.0
Summary: framework for estimating small probabilities using MCMC based on PyMC3-like probability model
Home-page: https://github.com/wlad111/pymc3
Author: Vladislav Strashko
Author-email: wlad962961@gmail.com
License: UNKNOWN
Platform: UNKNOWN
Classifier: Programming Language :: Python :: 3
Classifier: License :: OSI Approved :: Apache Software License
Classifier: Operating System :: OS Independent
Requires-Python: >=3.6
Requires-Dist: pymc3-ext-wlad
